{
  "section_id": "25-1-216",
  "content": "\n(A)\n\nExcept as provided in Subsection (B), a decision on a variance is effective immediately.\n\n(B)\n\nIf a variance is appealable, a decision on the variance is effective either:\n\n(1)\n\nat the expiration of the time period during which an appeal may be filed; or\n\n(2)\n\nif a notice of appeal is filed, when a final decision on the appeal is made.\n\nSource: City Code Section 25-1-216; Ord. 031211-11; Ord. 031211-42.\n\n(A)\n\nExcept as provided in Subsection (B), a variance expires:\n\n(1)\n\nexcept as provided in Subsection (A)(2), one year after the effective date of the\nvariance; or\n\n(2)\n\non the date established as a condition of approval.\n\n(B)\n\nA variance expires on the date an approved plan or permit expires if:\n\n(1)\n\nan application for approval of a plan or permit is submitted before a variance expires\nunder Subsection (A); or\n\n(2)\n\nthe variance is granted in association with the approved plan or permit.\n\nSource: City Code Section 25-1-217; Ord. 031211-11; Ord. 031211-42.",
  "entities": [
    {
      "text": "Section 25-1-216",
      "label": "SECTION_REF",
      "start": 363,
      "end": 379,
      "normalized": {
        "section": "25-1-216",
        "subsection": null,
        "full_reference": "25-1-216"
      }
    },
    {
      "text": "Section 25-1-217",
      "label": "SECTION_REF",
      "start": 928,
      "end": 944,
      "normalized": {
        "section": "25-1-217",
        "subsection": null,
        "full_reference": "25-1-217"
      }
    }
  ]
}